clip_text_decoder/__init__.py
clip_text_decoder/common.py
clip_text_decoder/datapipes.py
clip_text_decoder/dataset.py
clip_text_decoder/model.py
clip_text_decoder/utils/__init__.py
clip_text_decoder/utils/fileio.py
clip_text_decoder-1.4.4.dist-info/LICENSE
clip_text_decoder-1.4.4.dist-info/METADATA
clip_text_decoder-1.4.4.dist-info/WHEEL
clip_text_decoder-1.4.4.dist-info/top_level.txt
clip_text_decoder-1.4.4.dist-info/RECORD
