Metadata-Version: 2.1
Name: clip-text-decoder
Version: 1.4.4
Summary: Generate text captions for images from their CLIP embeddings.
Home-page: https://github.com/fkodom/clip-text-decoder
Author: Frank Odom
Author-email: frank.odom.iii@gmail.com
Classifier: Programming Language :: Python :: 3
Classifier: Operating System :: OS Independent
Requires-Python: >=3.7
License-File: LICENSE
Requires-Dist: evaluate
Requires-Dist: gdown
Requires-Dist: numpy
Requires-Dist: pytorch-lightning
Requires-Dist: spacy
Requires-Dist: torch (>=1.11)
Requires-Dist: torchdata (>=0.3.0)
Requires-Dist: torchvision
Requires-Dist: transformers
Requires-Dist: wget
Provides-Extra: test
Requires-Dist: black ; extra == 'test'
Requires-Dist: flake8 ; extra == 'test'
Requires-Dist: isort ; extra == 'test'
Requires-Dist: pre-commit ; extra == 'test'
Requires-Dist: pytest ; extra == 'test'
Requires-Dist: pytest-cov ; extra == 'test'
